tinyio/__init__.py
tinyio/_background.py
tinyio/_core.py
tinyio/_integrations.py
tinyio/_sync.py
tinyio/_thread.py
tinyio/_time.py
tinyio/_utils.py
tinyio-0.3.0.dist-info/METADATA
tinyio-0.3.0.dist-info/WHEEL
tinyio-0.3.0.dist-info/licenses/LICENSE
tinyio-0.3.0.dist-info/RECORD
