Metadata-Version: 2.4
Name: tinyio
Version: 0.3.0
Summary: A tiny event loop for Python.
Project-URL: repository, https://github.com/patrick-kidger/tinyio
Author-email: Patrick Kidger <contact@kidger.site>
License:                                  Apache License
License-File: LICENSE
Keywords: async,asyncio,await,tinyio
Classifier: Development Status :: 3 - Alpha
Classifier: License :: OSI Approved :: Apache Software License
Classifier: Natural Language :: English
Classifier: Programming Language :: Python :: 3
Requires-Python: >=3.11
Provides-Extra: dev
Requires-Dist: pre-commit; extra == 'dev'
Provides-Extra: tests
Requires-Dist: pytest; extra == 'tests'
Requires-Dist: trio; extra == 'tests'
